setup.py
hmq/__init__.py
hmq/hmq.py
hmq/test.py
hmq.egg-info/PKG-INFO
hmq.egg-info/SOURCES.txt
hmq.egg-info/dependency_links.txt
hmq.egg-info/entry_points.txt
hmq.egg-info/not-zip-safe
hmq.egg-info/requires.txt
hmq.egg-info/top_level.txt