Metadata-Version: 2.1
Name: hmq
Version: 25.4
Summary: Distributed computing.
Home-page: https://github.com/NablaChem/hummingqueue
Author: Guido Falk von Rudorff
Author-email: guido@vonrudorff.de
License: AGPL-3.0
Requires-Dist: dnspython
Requires-Dist: requests
Requires-Dist: cloudpickle
Requires-Dist: pynacl
Requires-Dist: tqdm
Requires-Dist: rq
Requires-Dist: toml
Requires-Dist: numpy
Requires-Dist: pandas
